rancher_gitlab_deploy/__init__.py
rancher_gitlab_deploy/cli.py
rancher_gitlab_deploy-1.7.dist-info/LICENSE
rancher_gitlab_deploy-1.7.dist-info/METADATA
rancher_gitlab_deploy-1.7.dist-info/WHEEL
rancher_gitlab_deploy-1.7.dist-info/entry_points.txt
rancher_gitlab_deploy-1.7.dist-info/top_level.txt
rancher_gitlab_deploy-1.7.dist-info/RECORD
