Metadata-Version: 2.1
Name: rancher-gitlab-deploy
Version: 1.7
Summary: Command line tool to ease updating services in Rancher from your GitLab CI pipeline
Home-page: https://github.com/cdrx/rancher-gitlab-deploy
Author: cdrx
Author-email: UNKNOWN
License: MIT
Platform: UNKNOWN
Requires-Dist: click
Requires-Dist: requests
Requires-Dist: colorama
